[
  {
    "label": "ČESKÁ REPUBLIKA",
    "id": "CZ"
  },
  {
    "label": "ČESKÁ REPUBLIKA",
    "id": "CZ0"
  },
  {
    "label": "Praha",
    "id": "CZ01"
  },
  {
    "label": "Hlavní město Praha",
    "id": "CZ010"
  },
  {
    "label": "Střední Čechy",
    "id": "CZ02"
  },
  {
    "label": "Středočeský kraj",
    "id": "CZ020"
  },
  {
    "label": "Jihozápad",
    "id": "CZ03"
  },
  {
    "label": "Jihočeský kraj",
    "id": "CZ031"
  },
  {
    "label": "Plzeňský kraj",
    "id": "CZ032"
  },
  {
    "label": "Severozápad",
    "id": "CZ04"
  },
  {
    "label": "Karlovarský kraj",
    "id": "CZ041"
  },
  {
    "label": "Ústecký kraj",
    "id": "CZ042"
  },
  {
    "label": "Severovýchod",
    "id": "CZ05"
  },
  {
    "label": "Liberecký kraj",
    "id": "CZ051"
  },
  {
    "label": "Královéhradecký kraj",
    "id": "CZ052"
  },
  {
    "label": "Pardubický kraj",
    "id": "CZ053"
  },
  {
    "label": "Jihovýchod",
    "id": "CZ06"
  },
  {
    "label": "Kraj Vysočina",
    "id": "CZ063"
  },
  {
    "label": "Jihomoravský kraj",
    "id": "CZ064"
  },
  {
    "label": "Střední Morava",
    "id": "CZ07"
  },
  {
    "label": "Olomoucký kraj",
    "id": "CZ071"
  },
  {
    "label": "Zlínský kraj",
    "id": "CZ072"
  },
  {
    "label": "Moravskoslezsko",
    "id": "CZ08"
  },
  {
    "label": "Moravskoslezský kraj",
    "id": "CZ080"
  },
  {
    "label": "EXTRA-REGIO NUTS 1",
    "id": "CZZ"
  },
  {
    "label": "Extra-Regio NUTS 2",
    "id": "CZZZ"
  },
  {
    "label": "Extra-Regio NUTS 3",
    "id": "CZZZZ"
  }
]